{
  "generated_at_utc": "2026-07-07T09:36:46.211241+00:00",
  "source": "yfinance",
  "interval": "1d",
  "lookback": "400d",
  "trading_days": 252,
  "count": 150,
  "data": [
    {
      "symbol": "SPCX",
      "name": "Space Exploration Technologies Corp",
      "price": 160.419998,
      "vol_annual": 1.37757588
    },
    {
      "symbol": "MU",
      "name": "Micron Technology",
      "price": 984.75,
      "vol_annual": 0.72862271
    },
    {
      "symbol": "NVDA",
      "name": "NVIDIA",
      "price": 195.550003,
      "vol_annual": 0.45403686
    },
    {
      "symbol": "SNDK",
      "name": "SanDisk",
      "price": 1744.430054,
      "vol_annual": 1.01697828
    },
    {
      "symbol": "TSLA",
      "name": "Tesla",
      "price": 419.769989,
      "vol_annual": 0.57834142
    },
    {
      "symbol": "AMD",
      "name": "Advanced Micro Devices",
      "price": 552.049988,
      "vol_annual": 0.6319639
    },
    {
      "symbol": "INTC",
      "name": "Intel",
      "price": 122.199997,
      "vol_annual": 0.7040203
    },
    {
      "symbol": "MRVL",
      "name": "Marvell Technology",
      "price": 249.270004,
      "vol_annual": 0.77032367
    },
    {
      "symbol": "AAPL",
      "name": "Apple",
      "price": 312.660004,
      "vol_annual": 0.29798232
    },
    {
      "symbol": "MSFT",
      "name": "Microsoft",
      "price": 386.73999,
      "vol_annual": 0.27505209
    },
    {
      "symbol": "AVGO",
      "name": "Broadcom",
      "price": 373.899994,
      "vol_annual": 0.54835715
    },
    {
      "symbol": "META",
      "name": "Meta Platforms",
      "price": 600.289978,
      "vol_annual": 0.38709822
    },
    {
      "symbol": "AMZN",
      "name": "Amazon",
      "price": 244.160004,
      "vol_annual": 0.32978594
    },
    {
      "symbol": "AMAT",
      "name": "Applied Materials",
      "price": 592.789978,
      "vol_annual": 0.51883639
    },
    {
      "symbol": "GOOG",
      "name": "Alphabet Class C",
      "price": 364.899994,
      "vol_annual": 0.31502297
    },
    {
      "symbol": "WDC",
      "name": "Western Digital",
      "price": 577.460022,
      "vol_annual": 0.65369256
    },
    {
      "symbol": "STX",
      "name": "Seagate Technology",
      "price": 868.26001,
      "vol_annual": 0.60760106
    },
    {
      "symbol": "PLTR",
      "name": "Palantir",
      "price": 132.539993,
      "vol_annual": 0.62965972
    },
    {
      "symbol": "LRCX",
      "name": "Lam Research",
      "price": 350.200012,
      "vol_annual": 0.55435557
    },
    {
      "symbol": "LITE",
      "name": "Lumentum Holdings",
      "price": 731.25,
      "vol_annual": 0.83897003
    },
    {
      "symbol": "KLAC",
      "name": "KLA Corporation",
      "price": 233.309998,
      "vol_annual": 0.52755864
    },
    {
      "symbol": "NBIS",
      "name": "Nebius Group",
      "price": 213.020004,
      "vol_annual": 1.09272226
    },
    {
      "symbol": "APP",
      "name": "AppLovin",
      "price": 543.789978,
      "vol_annual": 0.81549328
    },
    {
      "symbol": "ORCL",
      "name": "Oracle",
      "price": 143.759995,
      "vol_annual": 0.58041526
    },
    {
      "symbol": "ROKU",
      "name": "Roku",
      "price": 142.259995,
      "vol_annual": 0.54303002
    },
    {
      "symbol": "HOOD",
      "name": "Robinhood Markets",
      "price": 117.550003,
      "vol_annual": 0.7431327
    },
    {
      "symbol": "LLY",
      "name": "Eli Lilly",
      "price": 1200.060059,
      "vol_annual": 0.39444057
    },
    {
      "symbol": "GEV",
      "name": "GE Vernova",
      "price": 1152.040039,
      "vol_annual": 0.55464606
    },
    {
      "symbol": "XOM",
      "name": "Exxon Mobil",
      "price": 136.440002,
      "vol_annual": 0.25265641
    },
    {
      "symbol": "RKLB",
      "name": "Rocket Lab",
      "price": 93.089996,
      "vol_annual": 0.92578359
    },
    {
      "symbol": "QCOM",
      "name": "Qualcomm",
      "price": 186.479996,
      "vol_annual": 0.47279808
    },
    {
      "symbol": "NFLX",
      "name": "Netflix",
      "price": 76.019997,
      "vol_annual": 0.34797107
    },
    {
      "symbol": "DELL",
      "name": "Dell Technologies",
      "price": 411.799988,
      "vol_annual": 0.61955485
    },
    {
      "symbol": "AAOI",
      "name": "Applied Optoelectronics",
      "price": 123.360001,
      "vol_annual": 1.34516983
    },
    {
      "symbol": "AAL",
      "name": "American Airlines",
      "price": 17.75,
      "vol_annual": 0.53180057
    },
    {
      "symbol": "UNH",
      "name": "UnitedHealth Group",
      "price": 417.98999,
      "vol_annual": 0.47496527
    },
    {
      "symbol": "CSCO",
      "name": "Cisco Systems",
      "price": 113.980003,
      "vol_annual": 0.29394661
    },
    {
      "symbol": "MSTR",
      "name": "Strategy Inc.",
      "price": 100.769997,
      "vol_annual": 0.80342344
    },
    {
      "symbol": "JPM",
      "name": "JPMorgan Chase",
      "price": 337.720001,
      "vol_annual": 0.2448002
    },
    {
      "symbol": "GS",
      "name": "Goldman Sachs",
      "price": 1055.290039,
      "vol_annual": 0.31471656
    },
    {
      "symbol": "BE",
      "name": "Bloom Energy",
      "price": 295.049988,
      "vol_annual": 0.99654278
    },
    {
      "symbol": "WMT",
      "name": "Walmart",
      "price": 110.650002,
      "vol_annual": 0.25375735
    },
    {
      "symbol": "NOW",
      "name": "ServiceNow",
      "price": 107.93,
      "vol_annual": 0.49993081
    },
    {
      "symbol": "CRWV",
      "name": "CoreWeave",
      "price": 86.459999,
      "vol_annual": 1.10426305
    },
    {
      "symbol": "TXN",
      "name": "Texas Instruments",
      "price": 303.5,
      "vol_annual": 0.42736612
    },
    {
      "symbol": "CAT",
      "name": "Caterpillar",
      "price": 969.919983,
      "vol_annual": 0.3540281
    },
    {
      "symbol": "CRM",
      "name": "Salesforce",
      "price": 165.649994,
      "vol_annual": 0.3767823
    },
    {
      "symbol": "V",
      "name": "Visa",
      "price": 357.25,
      "vol_annual": 0.22852528
    },
    {
      "symbol": "COHR",
      "name": "Coherent",
      "price": 335.700012,
      "vol_annual": 0.77768135
    },
    {
      "symbol": "SATS",
      "name": "EchoStar",
      "price": 101.5,
      "vol_annual": 0.83146068
    },
    {
      "symbol": "PANW",
      "name": "Palo Alto Networks",
      "price": 357.529999,
      "vol_annual": 0.39477434
    },
    {
      "symbol": "ASTS",
      "name": "AST SpaceMobile",
      "price": 80.639999,
      "vol_annual": 1.02883782
    },
    {
      "symbol": "ALAB",
      "name": "Astera Labs",
      "price": 432.73999,
      "vol_annual": 0.94514765
    },
    {
      "symbol": "CRDO",
      "name": "Credo Technology Group",
      "price": 265.549988,
      "vol_annual": 0.99052171
    },
    {
      "symbol": "IREN",
      "name": "IREN Limited",
      "price": 43.91,
      "vol_annual": 1.02644914
    },
    {
      "symbol": "ADBE",
      "name": "Adobe",
      "price": 218.070007,
      "vol_annual": 0.36846752
    },
    {
      "symbol": "TER",
      "name": "Teradyne",
      "price": 379.519989,
      "vol_annual": 0.66588564
    },
    {
      "symbol": "BA",
      "name": "Boeing",
      "price": 234.539993,
      "vol_annual": 0.35818505
    },
    {
      "symbol": "ADI",
      "name": "Analog Devices",
      "price": 388.829987,
      "vol_annual": 0.38723502
    },
    {
      "symbol": "IBM",
      "name": "IBM",
      "price": 299.519989,
      "vol_annual": 0.37599012
    },
    {
      "symbol": "MA",
      "name": "Mastercard",
      "price": 533.099976,
      "vol_annual": 0.23156992
    },
    {
      "symbol": "SMCI",
      "name": "Super Micro Computer",
      "price": 27.190001,
      "vol_annual": 0.95761332
    },
    {
      "symbol": "HON",
      "name": "Honeywell",
      "price": 231.179993,
      "vol_annual": 0.2615177
    },
    {
      "symbol": "COST",
      "name": "Costco",
      "price": 950.25,
      "vol_annual": 0.2113098
    },
    {
      "symbol": "CVX",
      "name": "Chevron",
      "price": 168.100006,
      "vol_annual": 0.25029054
    },
    {
      "symbol": "CIEN",
      "name": "Ciena",
      "price": 433.829987,
      "vol_annual": 0.67193885
    },
    {
      "symbol": "JNJ",
      "name": "Johnson & Johnson",
      "price": 259.329987,
      "vol_annual": 0.19451641
    },
    {
      "symbol": "C",
      "name": "Citigroup",
      "price": 143.860001,
      "vol_annual": 0.31400782
    },
    {
      "symbol": "UBER",
      "name": "Uber",
      "price": 72.419998,
      "vol_annual": 0.3776832
    },
    {
      "symbol": "GE",
      "name": "GE Aerospace",
      "price": 378.679993,
      "vol_annual": 0.33059951
    },
    {
      "symbol": "BAC",
      "name": "Bank of America",
      "price": 59.900002,
      "vol_annual": 0.25633133
    },
    {
      "symbol": "MRK",
      "name": "Merck",
      "price": 126.779999,
      "vol_annual": 0.28992351
    },
    {
      "symbol": "CRWD",
      "name": "CrowdStrike",
      "price": 199.380005,
      "vol_annual": 0.47877531
    },
    {
      "symbol": "RGNT",
      "name": "Regentis Biomaterials",
      "price": 3.93,
      "vol_annual": 2.88181696
    },
    {
      "symbol": "GLW",
      "name": "Corning",
      "price": 194.800003,
      "vol_annual": 0.55055505
    },
    {
      "symbol": "VRT",
      "name": "Vertiv",
      "price": 318.470001,
      "vol_annual": 0.69899368
    },
    {
      "symbol": "BKNG",
      "name": "Booking Holdings",
      "price": 181.029999,
      "vol_annual": 0.32409099
    },
    {
      "symbol": "KO",
      "name": "Coca-Cola",
      "price": 82.959999,
      "vol_annual": 0.18005879
    },
    {
      "symbol": "IONQ",
      "name": "IonQ",
      "price": 48.869999,
      "vol_annual": 1.11232632
    },
    {
      "symbol": "HD",
      "name": "Home Depot",
      "price": 350.649994,
      "vol_annual": 0.24434842
    },
    {
      "symbol": "AMGN",
      "name": "Amgen",
      "price": 366.440002,
      "vol_annual": 0.27150514
    },
    {
      "symbol": "COIN",
      "name": "Coinbase",
      "price": 168.869995,
      "vol_annual": 0.72955448
    },
    {
      "symbol": "HPE",
      "name": "Hewlett Packard Enterprise",
      "price": 43.150002,
      "vol_annual": 0.50391762
    },
    {
      "symbol": "LIN",
      "name": "Linde",
      "price": 540.52002,
      "vol_annual": 0.19049748
    },
    {
      "symbol": "INTU",
      "name": "Intuit",
      "price": 272.140015,
      "vol_annual": 0.42636712
    },
    {
      "symbol": "APH",
      "name": "Amphenol",
      "price": 166.809998,
      "vol_annual": 0.42139775
    },
    {
      "symbol": "SNOW",
      "name": "Snowflake",
      "price": 262.089996,
      "vol_annual": 0.58028587
    },
    {
      "symbol": "COF",
      "name": "Capital One",
      "price": 206.5,
      "vol_annual": 0.35799493
    },
    {
      "symbol": "ON",
      "name": "ON Semiconductor",
      "price": 94.690002,
      "vol_annual": 0.63452614
    },
    {
      "symbol": "PG",
      "name": "Procter & Gamble",
      "price": 149.309998,
      "vol_annual": 0.19689453
    },
    {
      "symbol": "DDOG",
      "name": "Datadog",
      "price": 255.369995,
      "vol_annual": 0.56457753
    },
    {
      "symbol": "AXTI",
      "name": "AXT Inc.",
      "price": 63.52,
      "vol_annual": 1.25900442
    },
    {
      "symbol": "PEP",
      "name": "PepsiCo",
      "price": 143.289993,
      "vol_annual": 0.22289105
    },
    {
      "symbol": "SOFI",
      "name": "SoFi Technologies",
      "price": 18.610001,
      "vol_annual": 0.60677471
    },
    {
      "symbol": "CRCL",
      "name": "Circle Internet Group",
      "price": 68.650002,
      "vol_annual": 1.11308227
    },
    {
      "symbol": "FISV",
      "name": "Fiserv",
      "price": 51.779999,
      "vol_annual": 0.61755014
    },
    {
      "symbol": "MS",
      "name": "Morgan Stanley",
      "price": 222.100006,
      "vol_annual": 0.30605551
    },
    {
      "symbol": "MPWR",
      "name": "Monolithic Power Systems",
      "price": 1346.130005,
      "vol_annual": 0.57496668
    },
    {
      "symbol": "MCD",
      "name": "McDonald's",
      "price": 279.5,
      "vol_annual": 0.1850897
    },
    {
      "symbol": "ANET",
      "name": "Arista Networks",
      "price": 173.279999,
      "vol_annual": 0.57677298
    },
    {
      "symbol": "GOOGL",
      "name": "Alphabet Class A",
      "price": 366.459991,
      "vol_annual": 0.31896812
    },
    {
      "symbol": "TSM",
      "name": "Taiwan Semiconductor Manufacturing",
      "price": 451.790009,
      "vol_annual": 0.42252476
    },
    {
      "symbol": "ASML",
      "name": "ASML Holding",
      "price": 1825.069946,
      "vol_annual": 0.43682787
    },
    {
      "symbol": "NVO",
      "name": "Novo Nordisk",
      "price": 49.259998,
      "vol_annual": 0.52643943
    },
    {
      "symbol": "BRK-B",
      "name": "Berkshire Hathaway Class B",
      "price": 506.579987,
      "vol_annual": 0.17460288
    },
    {
      "symbol": "ABBV",
      "name": "AbbVie",
      "price": 254.759995,
      "vol_annual": 0.26605233
    },
    {
      "symbol": "TMO",
      "name": "Thermo Fisher Scientific",
      "price": 517.599976,
      "vol_annual": 0.31590126
    },
    {
      "symbol": "ABT",
      "name": "Abbott Laboratories",
      "price": 95.629997,
      "vol_annual": 0.2428199
    },
    {
      "symbol": "DHR",
      "name": "Danaher",
      "price": 193.619995,
      "vol_annual": 0.31094448
    },
    {
      "symbol": "ISRG",
      "name": "Intuitive Surgical",
      "price": 432.829987,
      "vol_annual": 0.33337812
    },
    {
      "symbol": "VRTX",
      "name": "Vertex Pharmaceuticals",
      "price": 529.590027,
      "vol_annual": 0.34571675
    },
    {
      "symbol": "GILD",
      "name": "Gilead Sciences",
      "price": 129.610001,
      "vol_annual": 0.27275203
    },
    {
      "symbol": "REGN",
      "name": "Regeneron Pharmaceuticals",
      "price": 649.809998,
      "vol_annual": 0.38325865
    },
    {
      "symbol": "MDT",
      "name": "Medtronic",
      "price": 83.059998,
      "vol_annual": 0.22773531
    },
    {
      "symbol": "CVS",
      "name": "CVS Health",
      "price": 102.080002,
      "vol_annual": 0.33994599
    },
    {
      "symbol": "PFE",
      "name": "Pfizer",
      "price": 23.719999,
      "vol_annual": 0.24902035
    },
    {
      "symbol": "BMY",
      "name": "Bristol Myers Squibb",
      "price": 56.700001,
      "vol_annual": 0.28048975
    },
    {
      "symbol": "AXP",
      "name": "American Express",
      "price": 356.029999,
      "vol_annual": 0.3009485
    },
    {
      "symbol": "SCHW",
      "name": "Charles Schwab",
      "price": 100.620003,
      "vol_annual": 0.26411692
    },
    {
      "symbol": "BLK",
      "name": "BlackRock",
      "price": 1011.210022,
      "vol_annual": 0.28041034
    },
    {
      "symbol": "SPGI",
      "name": "S&P Global",
      "price": 447.220001,
      "vol_annual": 0.28427226
    },
    {
      "symbol": "CME",
      "name": "CME Group",
      "price": 234.759995,
      "vol_annual": 0.21931353
    },
    {
      "symbol": "ICE",
      "name": "Intercontinental Exchange",
      "price": 134.910004,
      "vol_annual": 0.22496467
    },
    {
      "symbol": "MMC",
      "name": "Marsh & McLennan",
      "price": null,
      "vol_annual": null
    },
    {
      "symbol": "CB",
      "name": "Chubb",
      "price": 356.529999,
      "vol_annual": 0.19815685
    },
    {
      "symbol": "PGR",
      "name": "Progressive",
      "price": 231.669998,
      "vol_annual": 0.25539669
    },
    {
      "symbol": "T",
      "name": "AT&T",
      "price": 20.58,
      "vol_annual": 0.24323151
    },
    {
      "symbol": "VZ",
      "name": "Verizon",
      "price": 42.07,
      "vol_annual": 0.23648341
    },
    {
      "symbol": "CMCSA",
      "name": "Comcast",
      "price": 23.379999,
      "vol_annual": 0.30387611
    },
    {
      "symbol": "DIS",
      "name": "Walt Disney",
      "price": 97.410004,
      "vol_annual": 0.28663655
    },
    {
      "symbol": "ABNB",
      "name": "Airbnb",
      "price": 147.649994,
      "vol_annual": 0.35466682
    },
    {
      "symbol": "RTX",
      "name": "RTX Corporation",
      "price": 201.369995,
      "vol_annual": 0.2695441
    },
    {
      "symbol": "LMT",
      "name": "Lockheed Martin",
      "price": 538.0,
      "vol_annual": 0.27632886
    },
    {
      "symbol": "NOC",
      "name": "Northrop Grumman",
      "price": 547.75,
      "vol_annual": 0.28623303
    },
    {
      "symbol": "GD",
      "name": "General Dynamics",
      "price": 376.880005,
      "vol_annual": 0.22755761
    },
    {
      "symbol": "DE",
      "name": "Deere & Company",
      "price": 635.23999,
      "vol_annual": 0.30024867
    },
    {
      "symbol": "ETN",
      "name": "Eaton",
      "price": 413.420013,
      "vol_annual": 0.38117196
    },
    {
      "symbol": "EMR",
      "name": "Emerson Electric",
      "price": 141.559998,
      "vol_annual": 0.31836792
    },
    {
      "symbol": "PH",
      "name": "Parker-Hannifin",
      "price": 971.359985,
      "vol_annual": 0.29796814
    },
    {
      "symbol": "ITW",
      "name": "Illinois Tool Works",
      "price": 274.269989,
      "vol_annual": 0.22150194
    },
    {
      "symbol": "MMM",
      "name": "3M",
      "price": 159.149994,
      "vol_annual": 0.28400753
    },
    {
      "symbol": "UPS",
      "name": "United Parcel Service",
      "price": 110.019997,
      "vol_annual": 0.3255043
    },
    {
      "symbol": "FDX",
      "name": "FedEx",
      "price": 309.929993,
      "vol_annual": 0.32437987
    },
    {
      "symbol": "LOW",
      "name": "Lowe's",
      "price": 223.779999,
      "vol_annual": 0.25860643
    },
    {
      "symbol": "TGT",
      "name": "Target",
      "price": 126.099998,
      "vol_annual": 0.33258801
    },
    {
      "symbol": "NKE",
      "name": "Nike",
      "price": 43.34,
      "vol_annual": 0.40035628
    },
    {
      "symbol": "SBUX",
      "name": "Starbucks",
      "price": 102.110001,
      "vol_annual": 0.32289542
    },
    {
      "symbol": "CMG",
      "name": "Chipotle Mexican Grill",
      "price": 33.98,
      "vol_annual": 0.37921489
    },
    {
      "symbol": "MAR",
      "name": "Marriott International",
      "price": 379.75,
      "vol_annual": 0.28352454
    },
    {
      "symbol": "HLT",
      "name": "Hilton Worldwide",
      "price": 339.410004,
      "vol_annual": 0.25254986
    }
  ]
}